scikit.datasmooth-0.7.1-py3.6-nspkg.pth
scikit.datasmooth-0.7.1.dist-info/DESCRIPTION.rst
scikit.datasmooth-0.7.1.dist-info/METADATA
scikit.datasmooth-0.7.1.dist-info/RECORD
scikit.datasmooth-0.7.1.dist-info/WHEEL
scikit.datasmooth-0.7.1.dist-info/metadata.json
scikit.datasmooth-0.7.1.dist-info/namespace_packages.txt
scikit.datasmooth-0.7.1.dist-info/top_level.txt
scikit.datasmooth-0.7.1.dist-info/zip-safe
scikits/datasmooth/__init__.py
scikits/datasmooth/regularsmooth.py
